mcp_config_path/__init__.py
mcp_config_path/main.py
mcp_config_path-0.1.3.dist-info/METADATA
mcp_config_path-0.1.3.dist-info/WHEEL
mcp_config_path-0.1.3.dist-info/licenses/LICENSE
mcp_config_path-0.1.3.dist-info/RECORD
