Metadata-Version: 2.4
Name: mcp-config-path
Version: 0.1.3
Summary: mcp client config path, such as Claude Desktop and code, Cline, Cursor
Project-URL: homepage, https://github.com/milisp/mcp-config-path
Author-email: milisp <milisp@proton.me>
License-File: LICENSE
Requires-Python: >=3.8
